py2vision/__init__.py
py2vision/compute/__init__.py
py2vision/compute/error_compute.py
py2vision/compute/yolov3_calculus.py
py2vision/datasets_loader/__init__.py
py2vision/datasets_loader/yolov3_dataset_generator.py
py2vision/image_process/__init__.py
py2vision/image_process/frame_decorator.py
py2vision/image_process/resize.py
py2vision/image_process/resize_with_bbox.py
py2vision/image_process/rotate.py
py2vision/image_process/split_pair.py
py2vision/input_output/__init__.py
py2vision/input_output/camera.py
py2vision/input_output/vision_system.py
py2vision/models/__init__.py
py2vision/models/models_manager.py
py2vision/models/yolov3_model.py
py2vision/models/yolov3_tiny_model.py
py2vision/models/blocks/__init__.py
py2vision/models/blocks/backbone_block.py
py2vision/models/layers/__init__.py
py2vision/models/layers/batch_normalization_layer.py
py2vision/models/layers/conv2d_bn_leaky_relu_layer.py
py2vision/models/layers/residual_layer.py
py2vision/models/layers/upsample_layer.py
py2vision/recognition/__init__.py
py2vision/recognition/detection_mode.py
py2vision/recognition/selector.py
py2vision/recognition/yolov3_detector.py
py2vision/stereo/__init__.py
py2vision/stereo/match_method.py
py2vision/stereo/standard_stereo.py
py2vision/stereo/stereo_builder.py
py2vision/utils/__init__.py
py2vision/utils/annotations_helper.py
py2vision/utils/annotations_parser.py
py2vision/utils/draw.py
py2vision/utils/gen_pattern.py
py2vision/utils/label_utils.py
py2vision/utils/svgfig.py
py2vision-1.0.3.dist-info/LICENSE
py2vision-1.0.3.dist-info/METADATA
py2vision-1.0.3.dist-info/WHEEL
py2vision-1.0.3.dist-info/top_level.txt
py2vision-1.0.3.dist-info/RECORD
