Metadata-Version: 2.1
Name: py2vision
Version: 1.0.3
Summary: A package to implement a stereo vision system trained with deep learning
Home-page: https://github.com/corvus96/PyTwoVision
Author: Guillermo Jose Raven Lusinche
Author-email: guillermoraven96@gmail.com
License: MIT
Classifier: Programming Language :: Python :: 3
Classifier: License :: OSI Approved :: MIT License
Classifier: Operating System :: OS Independent
Classifier: Topic :: Scientific/Engineering :: Image Processing
Classifier: Topic :: Scientific/Engineering :: Image Recognition
Classifier: Topic :: Scientific/Engineering :: Information Analysis
Requires-Python: >=3.6
License-File: LICENSE
Requires-Dist: numpy (==1.21.5)
Requires-Dist: tensorflow (==2.8.0)
Requires-Dist: opencv-contrib-python (==4.6.0.66)
Requires-Dist: wget (==3.2)
Requires-Dist: pandas
Requires-Dist: pyyaml
Requires-Dist: h5py
